xposedornot/__init__.py
xposedornot/client.py
xposedornot/exceptions.py
xposedornot/models.py
xposedornot/py.typed
xposedornot/utils.py
xposedornot/endpoints/__init__.py
xposedornot/endpoints/breaches.py
xposedornot/endpoints/email.py
xposedornot/endpoints/password.py
xposedornot-1.0.1.dist-info/METADATA
xposedornot-1.0.1.dist-info/WHEEL
xposedornot-1.0.1.dist-info/licenses/LICENSE
xposedornot-1.0.1.dist-info/RECORD
