Metadata-Version: 2.4
Name: xposedornot
Version: 1.0.1
Summary: Python client for the XposedOrNot API - Check for data breaches and exposed credentials
Project-URL: Homepage, https://xposedornot.com
Project-URL: Documentation, https://xposedornot.com/api_doc
Project-URL: Repository, https://github.com/XposedOrNot/XposedOrNot-Python
Project-URL: Issues, https://github.com/XposedOrNot/XposedOrNot-Python/issues
Author-email: XposedOrNot <contact@xposedornot.com>
License-Expression: MIT
License-File: LICENSE
Keywords: breach,cybersecurity,data-breach,email,password,security,xposedornot
Classifier: Development Status :: 4 - Beta
Classifier: Intended Audience :: Developers
Classifier: License :: OSI Approved :: MIT License
Classifier: Operating System :: OS Independent
Classifier: Programming Language :: Python :: 3
Classifier: Programming Language :: Python :: 3.8
Classifier: Programming Language :: Python :: 3.9
Classifier: Programming Language :: Python :: 3.10
Classifier: Programming Language :: Python :: 3.11
Classifier: Programming Language :: Python :: 3.12
Classifier: Topic :: Security
Requires-Python: >=3.8
Requires-Dist: httpx>=0.24.0
Requires-Dist: pycryptodome>=3.15.0
Provides-Extra: dev
Requires-Dist: pytest-asyncio>=0.21.0; extra == 'dev'
Requires-Dist: pytest>=7.0.0; extra == 'dev'
Requires-Dist: respx>=0.20.0; extra == 'dev'
